csdnuploadimage/__init__.py
csdnuploadimage/core/__init__.py
csdnuploadimage/core/uploadImage.py
csdnuploadimage/utils/__init__.py
csdnuploadimage/utils/getUploadValidInfo.py
csdnuploadimage/utils/uploadImage.py
csdnuploadimage-2.0.dist-info/LICENSE
csdnuploadimage-2.0.dist-info/METADATA
csdnuploadimage-2.0.dist-info/WHEEL
csdnuploadimage-2.0.dist-info/top_level.txt
csdnuploadimage-2.0.dist-info/RECORD
