Metadata-Version: 2.1
Name: csdnuploadimage
Version: 2.0
Summary: 上传图片到csdn并返回图片url
Author: wqt
Author-email: 2916311184@qq.com
Classifier: Programming Language :: Python :: 3
Classifier: License :: OSI Approved :: MIT License
Classifier: Operating System :: OS Independent
Requires-Python: >=3.7
License-File: LICENSE
Requires-Dist: requests
